wowool/apps/themes/__init__.py
wowool/apps/themes/config.py
wowool/semantic_themes/__init__.py
wowool/semantic_themes/app_id.py
wowool/semantic_themes/themes.py
wowool/tools/semantic_themes/__main__.py
wowool/tools/semantic_themes/argument_parser.py
wowool_semantic_themes-3.2.0.dist-info/METADATA
wowool_semantic_themes-3.2.0.dist-info/WHEEL
wowool_semantic_themes-3.2.0.dist-info/entry_points.txt
wowool_semantic_themes-3.2.0.dist-info/top_level.txt
wowool_semantic_themes-3.2.0.dist-info/RECORD
