Metadata-Version: 2.1
Name: wowool-semantic-themes
Version: 3.2.0
Summary: Wowool Semantic Themes
Author: Wowool
Requires-Python: >=3.11
Requires-Dist: wowool-sdk
